{".class":"MypyFile","_fullname":"TodoAPP.routers.todos","future_import_flags":[],"is_partial_stub_package":false,"is_stub":false,"names":{".class":"SymbolTable","APIRouter":{".class":"SymbolTableNode","cross_ref":"fastapi.routing.APIRouter","kind":"Gdef"},"Annotated":{".class":"SymbolTableNode","cross_ref":"typing.Annotated","kind":"Gdef"},"BaseModel":{".class":"SymbolTableNode","cross_ref":"pydantic.main.BaseModel","kind":"Gdef"},"Depends":{".class":"SymbolTableNode","cross_ref":"fastapi.param_functions.Depends","kind":"Gdef"},"Field":{".class":"SymbolTableNode","cross_ref":"pydantic.fields.Field","kind":"Gdef"},"HTTPException":{".class":"SymbolTableNode","cross_ref":"fastapi.exceptions.HTTPException","kind":"Gdef"},"Path":{".class":"SymbolTableNode","cross_ref":"fastapi.param_functions.Path","kind":"Gdef"},"Session":{".class":"SymbolTableNode","cross_ref":"sqlalchemy.orm.session.Session","kind":"Gdef"},"SessionLocal":{".class":"SymbolTableNode","cross_ref":"TodoAPP.database.SessionLocal","kind":"Gdef"},"TodoRequest":{".class":"SymbolTableNode","kind":"Gdef","node":{".class":"TypeInfo","_promote":[],"abstract_attributes":[],"alt_promote":null,"bases":["pydantic.main.BaseModel"],"dataclass_transform_spec":null,"declared_metaclass":null,"defn":{".class":"ClassDef","fullname":"TodoAPP.routers.todos.TodoRequest","name":"TodoRequest","type_vars":[]},"deletable_attributes":[],"deprecated":null,"flags":[],"fullname":"TodoAPP.routers.todos.TodoRequest","has_param_spec_type":false,"metaclass_type":"pydantic._internal._model_construction.ModelMetaclass","metadata":{"dataclass":{"attributes":[{"alias":null,"column":4,"has_default":false,"is_in_init":false,"is_init_var":false,"is_neither_frozen_nor_nonfrozen":true,"kw_only":true,"line":175,"name":"__pydantic_extra__","type":{".class":"UnionType","items":[{".class":"Instance","args":["builtins.str",{".class":"AnyType","missing_import_name":null,"source_any":null,"type_of_any":2}],"extra_attrs":null,"type_ref":"builtins.dict"},{".class":"NoneType"}],"uses_pep604_syntax":true}},{"alias":null,"column":4,"has_default":false,"is_in_init":false,"is_init_var":false,"is_neither_frozen_nor_nonfrozen":true,"kw_only":true,"line":178,"name":"__pydantic_fields_set__","type":{".class":"Instance","args":["builtins.str"],"extra_attrs":null,"type_ref":"builtins.set"}},{"alias":null,"column":4,"has_default":false,"is_in_init":false,"is_init_var":false,"is_neither_frozen_nor_nonfrozen":true,"kw_only":true,"line":181,"name":"__pydantic_private__","type":{".class":"UnionType","items":[{".class":"Instance","args":["builtins.str",{".class":"AnyType","missing_import_name":null,"source_any":null,"type_of_any":2}],"extra_attrs":null,"type_ref":"builtins.dict"},{".class":"NoneType"}],"uses_pep604_syntax":true}},{"alias":null,"column":4,"has_default":false,"is_in_init":true,"is_init_var":false,"is_neither_frozen_nor_nonfrozen":false,"kw_only":true,"line":23,"name":"title","type":"builtins.str"},{"alias":null,"column":4,"has_default":false,"is_in_init":true,"is_init_var":false,"is_neither_frozen_nor_nonfrozen":false,"kw_only":true,"line":24,"name":"description","type":"builtins.str"},{"alias":null,"column":4,"has_default":false,"is_in_init":true,"is_init_var":false,"is_neither_frozen_nor_nonfrozen":false,"kw_only":true,"line":25,"name":"priority","type":"builtins.int"},{"alias":null,"column":4,"has_default":false,"is_in_init":true,"is_init_var":false,"is_neither_frozen_nor_nonfrozen":false,"kw_only":true,"line":26,"name":"completed","type":"builtins.bool"}],"frozen":false},"dataclass_tag":{}},"module_name":"TodoAPP.routers.todos","mro":["TodoAPP.routers.todos.TodoRequest","pydantic.main.BaseModel","builtins.object"],"names":{".class":"SymbolTable","__dataclass_fields__":{".class":"SymbolTableNode","kind":"Mdef","node":{".class":"Var","flags":["is_classvar","is_ready"],"fullname":"TodoAPP.routers.todos.TodoRequest.__dataclass_fields__","name":"__dataclass_fields__","type":{".class":"Instance","args":["builtins.str",{".class":"AnyType","missing_import_name":null,"source_any":null,"type_of_any":2}],"extra_attrs":null,"type_ref":"builtins.dict"}},"plugin_generated":true},"__init__":{".class":"SymbolTableNode","kind":"Mdef","node":{".class":"FuncDef","abstract_status":0,"arg_kinds":[0,3,3,3,3],"arg_names":["self","title","description","priority","completed"],"dataclass_transform_spec":null,"deprecated":null,"flags":[],"fullname":"TodoAPP.routers.todos.TodoRequest.__init__","name":"__init__","type":{".class":"CallableType","arg_kinds":[0,3,3,3,3],"arg_names":["self","title","description","priority","completed"],"arg_types":["TodoAPP.routers.todos.TodoRequest","builtins.str","builtins.str","builtins.int","builtins.bool"],"bound_args":[],"def_extras":{},"fallback":"builtins.function","from_concatenate":false,"implicit":false,"imprecise_arg_kinds":false,"is_ellipsis_args":false,"name":"__init__ of TodoRequest","ret_type":{".class":"NoneType"},"type_guard":null,"type_is":null,"unpack_kwargs":false,"variables":[]}},"plugin_generated":true},"__match_args__":{".class":"SymbolTableNode","kind":"Mdef","node":{".class":"Var","flags":["is_ready","allow_incompatible_override"],"fullname":"TodoAPP.routers.todos.TodoRequest.__match_args__","name":"__match_args__","type":{".class":"TupleType","implicit":false,"items":[{".class":"LiteralType","fallback":"builtins.str","value":"title"},{".class":"LiteralType","fallback":"builtins.str","value":"description"},{".class":"LiteralType","fallback":"builtins.str","value":"priority"},{".class":"LiteralType","fallback":"builtins.str","value":"completed"}],"partial_fallback":{".class":"Instance","args":[{".class":"AnyType","missing_import_name":null,"source_any":null,"type_of_any":6}],"extra_attrs":null,"type_ref":"builtins.tuple"}}},"plugin_generated":true},"__mypy-replace":{".class":"SymbolTableNode","kind":"Mdef","node":{".class":"Decorator","func":{".class":"FuncDef","abstract_status":0,"arg_kinds":[5,5,5,5,5,5,5],"arg_names":["__pydantic_extra__","__pydantic_fields_set__","__pydantic_private__","title","description","priority","completed"],"dataclass_transform_spec":null,"deprecated":null,"flags":["is_static","is_decorated"],"fullname":"TodoAPP.routers.todos.TodoRequest.__mypy-replace","name":"__mypy-replace","type":{".class":"CallableType","arg_kinds":[5,5,5,5,5,5,5],"arg_names":["__pydantic_extra__","__pydantic_fields_set__","__pydantic_private__","title","description","priority","completed"],"arg_types":[{".class":"UnionType","items":[{".class":"Instance","args":["builtins.str",{".class":"AnyType","missing_import_name":null,"source_any":null,"type_of_any":2}],"extra_attrs":null,"type_ref":"builtins.dict"},{".class":"NoneType"}],"uses_pep604_syntax":false},{".class":"Instance","args":["builtins.str"],"extra_attrs":null,"type_ref":"builtins.set"},{".class":"UnionType","items":[{".class":"Instance","args":["builtins.str",{".class":"AnyType","missing_import_name":null,"source_any":null,"type_of_any":2}],"extra_attrs":null,"type_ref":"builtins.dict"},{".class":"NoneType"}],"uses_pep604_syntax":false},"builtins.str","builtins.str","builtins.int","builtins.bool"],"bound_args":[],"def_extras":{},"fallback":"builtins.function","from_concatenate":false,"implicit":false,"imprecise_arg_kinds":false,"is_ellipsis_args":false,"name":"__mypy-replace of TodoRequest","ret_type":{".class":"NoneType"},"type_guard":null,"type_is":null,"unpack_kwargs":false,"variables":[]}},"is_overload":false,"var":{".class":"Var","flags":["is_staticmethod","is_ready"],"fullname":"TodoAPP.routers.todos.TodoRequest.__mypy-replace","name":"__mypy-replace","type":{".class":"CallableType","arg_kinds":[5,5,5,5,5,5,5],"arg_names":["__pydantic_extra__","__pydantic_fields_set__","__pydantic_private__","title","description","priority","completed"],"arg_types":[{".class":"UnionType","items":[{".class":"Instance","args":["builtins.str",{".class":"AnyType","missing_import_name":null,"source_any":null,"type_of_any":2}],"extra_attrs":null,"type_ref":"builtins.dict"},{".class":"NoneType"}],"uses_pep604_syntax":false},{".class":"Instance","args":["builtins.str"],"extra_attrs":null,"type_ref":"builtins.set"},{".class":"UnionType","items":[{".class":"Instance","args":["builtins.str",{".class":"AnyType","missing_import_name":null,"source_any":null,"type_of_any":2}],"extra_attrs":null,"type_ref":"builtins.dict"},{".class":"NoneType"}],"uses_pep604_syntax":false},"builtins.str","builtins.str","builtins.int","builtins.bool"],"bound_args":[],"def_extras":{},"fallback":"builtins.function","from_concatenate":false,"implicit":false,"imprecise_arg_kinds":false,"is_ellipsis_args":false,"name":"__mypy-replace of TodoRequest","ret_type":{".class":"NoneType"},"type_guard":null,"type_is":null,"unpack_kwargs":false,"variables":[]}}},"plugin_generated":true},"completed":{".class":"SymbolTableNode","kind":"Mdef","node":{".class":"Var","flags":["is_initialized_in_class","is_ready"],"fullname":"TodoAPP.routers.todos.TodoRequest.completed","name":"completed","type":"builtins.bool"}},"description":{".class":"SymbolTableNode","kind":"Mdef","node":{".class":"Var","flags":["is_initialized_in_class","is_ready","has_explicit_value"],"fullname":"TodoAPP.routers.todos.TodoRequest.description","name":"description","type":"builtins.str"}},"priority":{".class":"SymbolTableNode","kind":"Mdef","node":{".class":"Var","flags":["is_initialized_in_class","is_ready","has_explicit_value"],"fullname":"TodoAPP.routers.todos.TodoRequest.priority","name":"priority","type":"builtins.int"}},"title":{".class":"SymbolTableNode","kind":"Mdef","node":{".class":"Var","flags":["is_initialized_in_class","is_ready","has_explicit_value"],"fullname":"TodoAPP.routers.todos.TodoRequest.title","name":"title","type":"builtins.str"}}},"self_type":{".class":"TypeVarType","default":{".class":"AnyType","missing_import_name":null,"source_any":null,"type_of_any":4},"fullname":"TodoAPP.routers.todos.TodoRequest.Self","id":0,"name":"Self","namespace":"","upper_bound":"TodoAPP.routers.todos.TodoRequest","values":[],"variance":0},"slots":null,"tuple_type":null,"type_vars":[],"typeddict_type":null}},"Todos":{".class":"SymbolTableNode","cross_ref":"TodoAPP.models.Todos","kind":"Gdef"},"__annotations__":{".class":"SymbolTableNode","kind":"Gdef","node":{".class":"Var","flags":["is_ready"],"fullname":"TodoAPP.routers.todos.__annotations__","name":"__annotations__","type":{".class":"Instance","args":["builtins.str",{".class":"AnyType","missing_import_name":null,"source_any":null,"type_of_any":6}],"extra_attrs":null,"type_ref":"builtins.dict"}}},"__doc__":{".class":"SymbolTableNode","kind":"Gdef","node":{".class":"Var","flags":["is_ready"],"fullname":"TodoAPP.routers.todos.__doc__","name":"__doc__","type":"builtins.str"}},"__file__":{".class":"SymbolTableNode","kind":"Gdef","node":{".class":"Var","flags":["is_ready"],"fullname":"TodoAPP.routers.todos.__file__","name":"__file__","type":"builtins.str"}},"__name__":{".class":"SymbolTableNode","kind":"Gdef","node":{".class":"Var","flags":["is_ready"],"fullname":"TodoAPP.routers.todos.__name__","name":"__name__","type":"builtins.str"}},"__package__":{".class":"SymbolTableNode","kind":"Gdef","node":{".class":"Var","flags":["is_ready"],"fullname":"TodoAPP.routers.todos.__package__","name":"__package__","type":"builtins.str"}},"__spec__":{".class":"SymbolTableNode","kind":"Gdef","node":{".class":"Var","flags":["is_ready"],"fullname":"TodoAPP.routers.todos.__spec__","name":"__spec__","type":"_frozen_importlib.ModuleSpec"}},"create_todo":{".class":"SymbolTableNode","kind":"Gdef","node":{".class":"Decorator","func":{".class":"FuncDef","abstract_status":0,"arg_kinds":[0,0],"arg_names":["db","todo_request"],"dataclass_transform_spec":null,"deprecated":null,"flags":["is_coroutine","is_decorated"],"fullname":"TodoAPP.routers.todos.create_todo","name":"create_todo","type":{".class":"CallableType","arg_kinds":[0,0],"arg_names":["db","todo_request"],"arg_types":["sqlalchemy.orm.session.Session","TodoAPP.routers.todos.TodoRequest"],"bound_args":[],"def_extras":{"first_arg":null},"fallback":"builtins.function","from_concatenate":false,"implicit":false,"imprecise_arg_kinds":false,"is_ellipsis_args":false,"name":"create_todo","ret_type":{".class":"Instance","args":[{".class":"AnyType","missing_import_name":null,"source_any":null,"type_of_any":6},{".class":"AnyType","missing_import_name":null,"source_any":null,"type_of_any":6},{".class":"AnyType","missing_import_name":null,"source_any":null,"type_of_any":1}],"extra_attrs":null,"type_ref":"typing.Coroutine"},"type_guard":null,"type_is":null,"unpack_kwargs":false,"variables":[]}},"is_overload":false,"var":{".class":"Var","flags":["is_ready","is_inferred"],"fullname":"TodoAPP.routers.todos.create_todo","name":"create_todo","type":{".class":"CallableType","arg_kinds":[0,0],"arg_names":["db","todo_request"],"arg_types":["sqlalchemy.orm.session.Session","TodoAPP.routers.todos.TodoRequest"],"bound_args":[],"def_extras":{"first_arg":null},"fallback":"builtins.function","from_concatenate":false,"implicit":false,"imprecise_arg_kinds":false,"is_ellipsis_args":false,"name":"create_todo","ret_type":{".class":"Instance","args":[{".class":"AnyType","missing_import_name":null,"source_any":null,"type_of_any":6},{".class":"AnyType","missing_import_name":null,"source_any":null,"type_of_any":6},{".class":"AnyType","missing_import_name":null,"source_any":null,"type_of_any":1}],"extra_attrs":null,"type_ref":"typing.Coroutine"},"type_guard":null,"type_is":null,"unpack_kwargs":false,"variables":[]}}}},"db_dependency":{".class":"SymbolTableNode","kind":"Gdef","node":{".class":"TypeAlias","alias_tvars":[],"column":0,"fullname":"TodoAPP.routers.todos.db_dependency","line":20,"no_args":true,"normalized":false,"python_3_12_type_alias":false,"target":"sqlalchemy.orm.session.Session"}},"delete_todo":{".class":"SymbolTableNode","kind":"Gdef","node":{".class":"Decorator","func":{".class":"FuncDef","abstract_status":0,"arg_kinds":[0,1],"arg_names":["db","todo_id"],"dataclass_transform_spec":null,"deprecated":null,"flags":["is_coroutine","is_decorated"],"fullname":"TodoAPP.routers.todos.delete_todo","name":"delete_todo","type":{".class":"CallableType","arg_kinds":[0,1],"arg_names":["db","todo_id"],"arg_types":["sqlalchemy.orm.session.Session","builtins.int"],"bound_args":[],"def_extras":{"first_arg":null},"fallback":"builtins.function","from_concatenate":false,"implicit":false,"imprecise_arg_kinds":false,"is_ellipsis_args":false,"name":"delete_todo","ret_type":{".class":"Instance","args":[{".class":"AnyType","missing_import_name":null,"source_any":null,"type_of_any":6},{".class":"AnyType","missing_import_name":null,"source_any":null,"type_of_any":6},{".class":"AnyType","missing_import_name":null,"source_any":null,"type_of_any":1}],"extra_attrs":null,"type_ref":"typing.Coroutine"},"type_guard":null,"type_is":null,"unpack_kwargs":false,"variables":[]}},"is_overload":false,"var":{".class":"Var","flags":["is_ready","is_inferred"],"fullname":"TodoAPP.routers.todos.delete_todo","name":"delete_todo","type":{".class":"CallableType","arg_kinds":[0,1],"arg_names":["db","todo_id"],"arg_types":["sqlalchemy.orm.session.Session","builtins.int"],"bound_args":[],"def_extras":{"first_arg":null},"fallback":"builtins.function","from_concatenate":false,"implicit":false,"imprecise_arg_kinds":false,"is_ellipsis_args":false,"name":"delete_todo","ret_type":{".class":"Instance","args":[{".class":"AnyType","missing_import_name":null,"source_any":null,"type_of_any":6},{".class":"AnyType","missing_import_name":null,"source_any":null,"type_of_any":6},{".class":"AnyType","missing_import_name":null,"source_any":null,"type_of_any":1}],"extra_attrs":null,"type_ref":"typing.Coroutine"},"type_guard":null,"type_is":null,"unpack_kwargs":false,"variables":[]}}}},"get_db":{".class":"SymbolTableNode","kind":"Gdef","node":{".class":"FuncDef","abstract_status":0,"arg_kinds":[],"arg_names":[],"dataclass_transform_spec":null,"deprecated":null,"flags":["is_generator"],"fullname":"TodoAPP.routers.todos.get_db","name":"get_db","type":null}},"read_all":{".class":"SymbolTableNode","kind":"Gdef","node":{".class":"Decorator","func":{".class":"FuncDef","abstract_status":0,"arg_kinds":[0],"arg_names":["db"],"dataclass_transform_spec":null,"deprecated":null,"flags":["is_coroutine","is_decorated"],"fullname":"TodoAPP.routers.todos.read_all","name":"read_all","type":{".class":"CallableType","arg_kinds":[0],"arg_names":["db"],"arg_types":["sqlalchemy.orm.session.Session"],"bound_args":[],"def_extras":{"first_arg":null},"fallback":"builtins.function","from_concatenate":false,"implicit":false,"imprecise_arg_kinds":false,"is_ellipsis_args":false,"name":"read_all","ret_type":{".class":"Instance","args":[{".class":"AnyType","missing_import_name":null,"source_any":null,"type_of_any":6},{".class":"AnyType","missing_import_name":null,"source_any":null,"type_of_any":6},{".class":"AnyType","missing_import_name":null,"source_any":null,"type_of_any":1}],"extra_attrs":null,"type_ref":"typing.Coroutine"},"type_guard":null,"type_is":null,"unpack_kwargs":false,"variables":[]}},"is_overload":false,"var":{".class":"Var","flags":["is_ready","is_inferred"],"fullname":"TodoAPP.routers.todos.read_all","name":"read_all","type":{".class":"CallableType","arg_kinds":[0],"arg_names":["db"],"arg_types":["sqlalchemy.orm.session.Session"],"bound_args":[],"def_extras":{"first_arg":null},"fallback":"builtins.function","from_concatenate":false,"implicit":false,"imprecise_arg_kinds":false,"is_ellipsis_args":false,"name":"read_all","ret_type":{".class":"Instance","args":[{".class":"AnyType","missing_import_name":null,"source_any":null,"type_of_any":6},{".class":"AnyType","missing_import_name":null,"source_any":null,"type_of_any":6},{".class":"AnyType","missing_import_name":null,"source_any":null,"type_of_any":1}],"extra_attrs":null,"type_ref":"typing.Coroutine"},"type_guard":null,"type_is":null,"unpack_kwargs":false,"variables":[]}}}},"read_todo":{".class":"SymbolTableNode","kind":"Gdef","node":{".class":"Decorator","func":{".class":"FuncDef","abstract_status":0,"arg_kinds":[0,1],"arg_names":["db","todo_id"],"dataclass_transform_spec":null,"deprecated":null,"flags":["is_coroutine","is_decorated"],"fullname":"TodoAPP.routers.todos.read_todo","name":"read_todo","type":{".class":"CallableType","arg_kinds":[0,1],"arg_names":["db","todo_id"],"arg_types":["sqlalchemy.orm.session.Session","builtins.int"],"bound_args":[],"def_extras":{"first_arg":null},"fallback":"builtins.function","from_concatenate":false,"implicit":false,"imprecise_arg_kinds":false,"is_ellipsis_args":false,"name":"read_todo","ret_type":{".class":"Instance","args":[{".class":"AnyType","missing_import_name":null,"source_any":null,"type_of_any":6},{".class":"AnyType","missing_import_name":null,"source_any":null,"type_of_any":6},{".class":"AnyType","missing_import_name":null,"source_any":null,"type_of_any":1}],"extra_attrs":null,"type_ref":"typing.Coroutine"},"type_guard":null,"type_is":null,"unpack_kwargs":false,"variables":[]}},"is_overload":false,"var":{".class":"Var","flags":["is_ready","is_inferred"],"fullname":"TodoAPP.routers.todos.read_todo","name":"read_todo","type":{".class":"CallableType","arg_kinds":[0,1],"arg_names":["db","todo_id"],"arg_types":["sqlalchemy.orm.session.Session","builtins.int"],"bound_args":[],"def_extras":{"first_arg":null},"fallback":"builtins.function","from_concatenate":false,"implicit":false,"imprecise_arg_kinds":false,"is_ellipsis_args":false,"name":"read_todo","ret_type":{".class":"Instance","args":[{".class":"AnyType","missing_import_name":null,"source_any":null,"type_of_any":6},{".class":"AnyType","missing_import_name":null,"source_any":null,"type_of_any":6},{".class":"AnyType","missing_import_name":null,"source_any":null,"type_of_any":1}],"extra_attrs":null,"type_ref":"typing.Coroutine"},"type_guard":null,"type_is":null,"unpack_kwargs":false,"variables":[]}}}},"router":{".class":"SymbolTableNode","kind":"Gdef","node":{".class":"Var","flags":["is_inferred","has_explicit_value"],"fullname":"TodoAPP.routers.todos.router","name":"router","type":"fastapi.routing.APIRouter"}},"status":{".class":"SymbolTableNode","cross_ref":"starlette.status","kind":"Gdef"},"update_todo":{".class":"SymbolTableNode","kind":"Gdef","node":{".class":"Decorator","func":{".class":"FuncDef","abstract_status":0,"arg_kinds":[0,1,1],"arg_names":["db","todo_request","todo_id"],"dataclass_transform_spec":null,"deprecated":null,"flags":["is_coroutine","is_decorated"],"fullname":"TodoAPP.routers.todos.update_todo","name":"update_todo","type":{".class":"CallableType","arg_kinds":[0,1,1],"arg_names":["db","todo_request","todo_id"],"arg_types":["sqlalchemy.orm.session.Session",{".class":"AnyType","missing_import_name":null,"source_any":null,"type_of_any":1},"builtins.int"],"bound_args":[],"def_extras":{"first_arg":null},"fallback":"builtins.function","from_concatenate":false,"implicit":false,"imprecise_arg_kinds":false,"is_ellipsis_args":false,"name":"update_todo","ret_type":{".class":"Instance","args":[{".class":"AnyType","missing_import_name":null,"source_any":null,"type_of_any":6},{".class":"AnyType","missing_import_name":null,"source_any":null,"type_of_any":6},{".class":"AnyType","missing_import_name":null,"source_any":null,"type_of_any":1}],"extra_attrs":null,"type_ref":"typing.Coroutine"},"type_guard":null,"type_is":null,"unpack_kwargs":false,"variables":[]}},"is_overload":false,"var":{".class":"Var","flags":["is_ready","is_inferred"],"fullname":"TodoAPP.routers.todos.update_todo","name":"update_todo","type":{".class":"CallableType","arg_kinds":[0,1,1],"arg_names":["db","todo_request","todo_id"],"arg_types":["sqlalchemy.orm.session.Session",{".class":"AnyType","missing_import_name":null,"source_any":null,"type_of_any":1},"builtins.int"],"bound_args":[],"def_extras":{"first_arg":null},"fallback":"builtins.function","from_concatenate":false,"implicit":false,"imprecise_arg_kinds":false,"is_ellipsis_args":false,"name":"update_todo","ret_type":{".class":"Instance","args":[{".class":"AnyType","missing_import_name":null,"source_any":null,"type_of_any":6},{".class":"AnyType","missing_import_name":null,"source_any":null,"type_of_any":6},{".class":"AnyType","missing_import_name":null,"source_any":null,"type_of_any":1}],"extra_attrs":null,"type_ref":"typing.Coroutine"},"type_guard":null,"type_is":null,"unpack_kwargs":false,"variables":[]}}}}},"path":"C:\\Python_py\\Test\\TodoAPP\\routers\\todos.py"}